{
  "schemaVersion": 1,
  "id": "additionalbars",
  "version": "${version}",

  "name": "Additional Bars",
  "description": "This mod adds additional bars to the game that go along with Iron Bars!",
  "authors": [
    "CodenameRevy",
    "ruchom4u (Spanish Translations)",
    "fantasyair18 (Chinese Traditional (Taiwan) Translations)",
    "TheDirectorX (Russian Translations)",
    "BardinTheDwarf (Russian Translations)",
    "Zijuna (German Translations)",
    "justmonika (Simple Chinese Translations)",
    "mindy15963 (Korean Translations)",
    "WadeMason"
  ],
  "contact": {
    "homepage": "https://fabricmc.net/",
    "sources": "https://github.com/CodenameRevy/additional-bars-fabric"
  },

  "license": "MIT License",
  "icon": "assets/additionalbars/icon.png",

  "environment": "*",
  "entrypoints": {
    "main": [
      "com.codenamerevy.additionalbars.AdditionalBars"
    ]
  },

  "depends": {
    "fabricloader": ">=0.7.4",
    "fabric": "*",
    "minecraft": "1.16.x"
  },
  "suggests": {
    "another-mod": "*"
  }
}
