{
  "parent": "minecraft:recipes/root",
  "criteria": {
    "has_crossed_exposed_copper_bars": {
      "conditions": {
        "items": [
          {
            "items": "additionalbars:crossed_exposed_copper_bars"
          }
        ]
      },
      "trigger": "minecraft:inventory_changed"
    },
    "has_exposed_copper_bars": {
      "conditions": {
        "items": [
          {
            "items": "additionalbars:exposed_copper_bars"
          }
        ]
      },
      "trigger": "minecraft:inventory_changed"
    },
    "has_the_recipe": {
      "conditions": {
        "recipe": "additionalbars:crossed_exposed_copper_bars"
      },
      "trigger": "minecraft:recipe_unlocked"
    }
  },
  "requirements": [
    [
      "has_the_recipe",
      "has_crossed_exposed_copper_bars",
      "has_exposed_copper_bars"
    ]
  ],
  "rewards": {
    "recipes": [
      "additionalbars:crossed_exposed_copper_bars"
    ]
  }
}